Workbook

Sheet Transactions
A1: Transaction ID | B1: Date | C1: Type | D1: Buyer Company | E1: Seller Company | F1: Product / Item | G1: Quantity | H1: Unit Price (₹) | I1: Total Amount (₹) | J1: Payment Status | K1: Amount Paid (₹) | L1: Balance Due (₹) | M1: Payment Due Date | N1: Delivery Status | O1: Expected Delivery | P1: Notes
A2: TXN-0001 | B2: 46056 | C2: Buy | D2: ABC Enterprises | E2: XYZ Traders | F2: Office Chairs | G2: 10 | H2: 2500 | I2: =IF(G2*H2=0,"",G2*H2) | J2: Paid | K2: 25000 | L2: =IF(I2="","",I2-IF(K2="",0,K2)) | M2: 46086 | N2: Delivered | O2: 46071 | P2: Bulk order for new office wing
A3: TXN-0002 | B3: 46071 | C3: Sell | D3: Sunrise Retail Co. | E3: ABC Enterprises | F3: LED Strip Lights | G3: 50 | H3: 350 | I3: =IF(G3*H3=0,"",G3*H3) | J3: Paid | K3: 17500 | L3: =IF(I3="","",I3-IF(K3="",0,K3)) | M3: 46091 | N3: Delivered | O3: 46081 | P3: Monthly supply contract
A4: TXN-0003 | B4: 46081 | C4: Buy | D4: ABC Enterprises | E4: Metro Supplies Ltd. | F4: A4 Paper (Box) | G4: 100 | H4: 480 | I4: =IF(G4*H4=0,"",G4*H4) | J4: Paid | K4: 48000 | L4: =IF(I4="","",I4-IF(K4="",0,K4)) | M4: 46096 | N4: Delivered | O4: 46089 | P4: Stationery restock Q1
A5: TXN-0004 | B5: 46083 | C5: Sell | D5: Greenleaf Corp. | E5: ABC Enterprises | F5: Laptop Bags | G5: 30 | H5: 750 | I5: =IF(G5*H5=0,"",G5*H5) | J5: Paid | K5: 22500 | L5: =IF(I5="","",I5-IF(K5="",0,K5)) | M5: 46093 | N5: Delivered | O5: 46086 | P5: Corporate gift order
A6: TXN-0005 | B6: 46086 | C6: Buy | D6: ABC Enterprises | E6: TechZone Pvt. Ltd. | F6: USB-C Hubs | G6: 20 | H6: 1200 | I6: =IF(G6*H6=0,"",G6*H6) | J6: Pending | K6: 0 | L6: =IF(I6="","",I6-IF(K6="",0,K6)) | M6: 46116 | N6: Pending | O6: 46111 | P6: Awaiting delivery confirmation
A7: TXN-0006 | B7: 46089 | C7: Sell | D7: BlueStar Industries | E7: ABC Enterprises | F7: Printer Cartridges | G7: 60 | H7: 320 | I7: =IF(G7*H7=0,"",G7*H7) | J7: Pending | K7: 0 | L7: =IF(I7="","",I7-IF(K7="",0,K7)) | M7: 46119 | N7: Delivered | O7: 46096 | P7: Invoice sent; awaiting payment
A8: TXN-0007 | B8: 46091 | C8: Buy | D8: ABC Enterprises | E8: Global Furniture Co. | F8: Standing Desks | G8: 8 | H8: 8500 | I8: =IF(G8*H8=0,"",G8*H8) | J8: Pending | K8: 34000 | L8: =IF(I8="","",I8-IF(K8="",0,K8)) | M8: 46121 | N8: Pending | O8: 46126 | P8: Partial advance paid; balance on delivery
A9: TXN-0008 | B9: 46093 | C9: Sell | D9: Horizon Traders | E9: ABC Enterprises | F9: Wireless Keyboards | G9: 25 | H9: 950 | I9: =IF(G9*H9=0,"",G9*H9) | J9: Pending | K9: 0 | L9: =IF(I9="","",I9-IF(K9="",0,K9)) | M9: 46113 | N9: Pending | O9: 46109 | P9: Order confirmed; production in progress
A10: TXN-0009 | B10: 46066 | C10: Buy | D10: ABC Enterprises | E10: Speedy Logistics | F10: Packaging Material | G10: 200 | H10: 150 | I10: =IF(G10*H10=0,"",G10*H10) | J10: Due | K10: 0 | L10: =IF(I10="","",I10-IF(K10="",0,K10)) | M10: 46091 | N10: Delivered | O10: 46073 | P10: Payment overdue — follow up with accounts
A11: TXN-0010 | B11: 46076 | C11: Sell | D11: Redwood Distributors | E11: ABC Enterprises | F11: Steel Shelving Units | G11: 15 | H11: 3200 | I11: =IF(G11*H11=0,"",G11*H11) | J11: Due | K11: 16000 | L11: =IF(I11="","",I11-IF(K11="",0,K11)) | M11: 46096 | N11: Delivered | O11: 46083 | P11: Partial payment received; balance due
A12: TXN-0011 | B12: 46079 | C12: Buy | D12: ABC Enterprises | E12: Alpha Electronics | F12: HDMI Cables (pack) | G12: 80 | H12: 220 | I12: =IF(G12*H12=0,"",G12*H12) | J12: Due | K12: 0 | L12: =IF(I12="","",I12-IF(K12="",0,K12)) | M12: 46099 | N12: Delivered | O12: 46081 | P12: Urgent: payment deadline crossed
A13: TXN-0012 | B13: 46096 | C13: Sell | D13: Pinnacle Group | E13: ABC Enterprises | F13: Office Sofas | G13: 5 | H13: 12000 | I13: =IF(G13*H13=0,"",G13*H13) | J13: Pending | K13: 0 | L13: =IF(I13="","",I13-IF(K13="",0,K13)) | M13: 46131 | N13: Pending | O13: 46146 | P13: Custom order; 45-day delivery window
... A17: TXN-0016 | B17: 46101 | C17: Sell | D17: Eastgate Wholesalers | E17: ABC Enterprises | F17: Projector Screens | G17: 10 | H17: 4500 | I17: =IF(G17*H17=0,"",G17*H17) | J17: Pending | K17: 0 | L17: =IF(I17="","",I17-IF(K17="",0,K17)) | M17: 46116 | N17: Pending | O17: 46121 | P17: New bulk deal — first transaction
I18: =IF(G18*H18=0,"",G18*H18) | L18: =IF(I18="","",I18-IF(K18="",0,K18))
I19: =IF(G19*H19=0,"",G19*H19) | L19: =IF(I19="","",I19-IF(K19="",0,K19))
I20: =IF(G20*H20=0,"",G20*H20) | L20: =IF(I20="","",I20-IF(K20="",0,K20))
I21: =IF(G21*H21=0,"",G21*H21) | L21: =IF(I21="","",I21-IF(K21="",0,K21))
I22: =IF(G22*H22=0,"",G22*H22) | L22: =IF(I22="","",I22-IF(K22="",0,K22))
I23: =IF(G23*H23=0,"",G23*H23) | L23: =IF(I23="","",I23-IF(K23="",0,K23))
I24: =IF(G24*H24=0,"",G24*H24) | L24: =IF(I24="","",I24-IF(K24="",0,K24))
I25: =IF(G25*H25=0,"",G25*H25) | L25: =IF(I25="","",I25-IF(K25="",0,K25))
I26: =IF(G26*H26=0,"",G26*H26) | L26: =IF(I26="","",I26-IF(K26="",0,K26))
I27: =IF(G27*H27=0,"",G27*H27) | L27: =IF(I27="","",I27-IF(K27="",0,K27))
I28: =IF(G28*H28=0,"",G28*H28) | L28: =IF(I28="","",I28-IF(K28="",0,K28))
I29: =IF(G29*H29=0,"",G29*H29) | L29: =IF(I29="","",I29-IF(K29="",0,K29))
... I501: =IF(G501*H501=0,"",G501*H501) | L501: =IF(I501="","",I501-IF(K501="",0,K501))

Sheet Dashboard
B2: Transaction Management — Dashboard
B3: Auto-updated from Transactions sheet | Generated: 20 Mar 2026
B5: 📋 OVERVIEW
B6: Total Transactions | C6: =COUNTA(Transactions!A2:A501)-COUNTIF(Transactions!A2:A501,"")
B7: Total Transaction Value (₹) | C7: =IFERROR(SUM(Transactions!I2:I501),0)
B8: Buy Transactions | C8: =COUNTIF(Transactions!C2:C501,"Buy")
B9: Sell Transactions | C9: =COUNTIF(Transactions!C2:C501,"Sell")
B11: 💳 PAYMENT STATUS
B12: Paid — Count | C12: =COUNTIF(Transactions!J2:J501,"Paid")
B13: Paid — Total Amount (₹) | C13: =IFERROR(SUMIF(Transactions!J2:J501,"Paid",Transactions!I2:I501),0)
B14: Pending — Count | C14: =COUNTIF(Transactions!J2:J501,"Pending")
B15: Pending — Total Amount (₹) | C15: =IFERROR(SUMIF(Transactions!J2:J501,"Pending",Transactions!I2:I501),0)
B16: Due / Overdue — Count | C16: =COUNTIF(Transactions!J2:J501,"Due")
B17: Due / Overdue — Total Amount (₹) | C17: =IFERROR(SUMIF(Transactions!J2:J501,"Due",Transactions!I2:I501),0)
B18: Total Balance Due (₹) | C18: =IFERROR(SUM(Transactions!L2:L501),0)
B20: 🚚 DELIVERY STATUS
B21: Delivered — Count | C21: =COUNTIF(Transactions!N2:N501,"Delivered")
B22: Delivery Pending — Count | C22: =COUNTIF(Transactions!N2:N501,"Pending")
B24: All values are automatically calculated from the Transactions sheet.

Sheet Instructions
B1: How to Use — Transaction Management Sheet
B3: GETTING STARTED
B4: Step 1 | C4: Go to the 'Transactions' sheet to enter data.
B5: Step 2 | C5: Fill in each column from left to right for every transaction.
B6: Step 3 | C6: The 'Total Amount' and 'Balance Due' columns calculate automatically — do not edit them.
B7: Step 4 | C7: Check the 'Dashboard' sheet for a live summary of all transactions.
B8: COLUMN GUIDE
B9: Transaction ID | C9: Enter a unique ID for each transaction (e.g., TXN-0001, TXN-0002, ...).
B10: Date | C10: The date the transaction was made (DD/MM/YYYY).
B11: Type | C11: Select 'Buy' if your company is purchasing, 'Sell' if selling. Choose from dropdown.
B12: Buyer Company | C12: Name of the company that is buying goods/services.
B13: Seller Company | C13: Name of the company that is selling goods/services.
B14: Product / Item | C14: Name of the product or service. For multiple items, separate with commas.
B15: Quantity | C15: Number of units.
B16: Unit Price (₹) | C16: Price per unit in Indian Rupees.
B17: Total Amount | C17: AUTO-CALCULATED: Quantity × Unit Price. Do not edit.
B18: Payment Status | C18: Select from dropdown: Paid / Pending / Due.
B19: Amount Paid | C19: How much has already been paid (partial or full).
B20: Balance Due | C20: AUTO-CALCULATED: Total Amount - Amount Paid. Do not edit.
... B24: Notes | C24: Any additional remarks, terms, or conditions.
B25: COLOUR CODES
B26: Green (Payment) | C26: Payment has been received — Paid.
B27: Yellow/Orange | C27: Payment is Pending — action needed.
B28: Red | C28: Payment is Due or Overdue — urgent.
B29: Red row (full) | C29: Entire row turns light red when Payment Due Date has passed and payment is not Paid.
B30: Blue (Delivery) | C30: Item has been Delivered successfully.
B31: TIPS
B32: Filtering | C32: Use the dropdown arrows in the header row of Transactions to filter by any column.
B33: Sorting | C33: Click any header to sort transactions by that column.
B34: Adding rows | C34: Simply type in the next empty row — all formatting and formulas apply automatically.
B35: Dashboard | C35: The Dashboard sheet updates automatically as you add or edit transactions.
